host_inspector/__init__.py
host_inspector/date_time.py
host_inspector/disk.py
host_inspector/machine.py
host_inspector/memory.py
host_inspector/network.py
host_inspector/python.py
host_inspector/uptime.py
host_inspector/cpu/__init__.py
host_inspector/cpu/linux.py
host_inspector/cpu/mac.py
host_inspector/cpu/utils.py
host_inspector/cpu/windows.py
host_inspector/display/__init__.py
host_inspector/display/linux.py
host_inspector/display/mac.py
host_inspector/display/windows.py
host_inspector/firewall/__init__.py
host_inspector/firewall/linux.py
host_inspector/firewall/mac.py
host_inspector/firewall/windows.py
host_inspector/gpu/__init__.py
host_inspector/gpu/linux.py
host_inspector/gpu/mac.py
host_inspector/gpu/utils.py
host_inspector/gpu/windows.py
host_inspector/os/__init__.py
host_inspector/os/linux.py
host_inspector/os/mac.py
host_inspector/os/windows.py
host_inspector/platform/__init__.py
host_inspector/platform/linux.py
host_inspector/platform/mac.py
host_inspector/platform/windows.py
host_inspector/utils/__init__.py
host_inspector/utils/byteutils.py
host_inspector/utils/datetimeutils.py
host_inspector/utils/importutils.py
host_inspector/utils/processutils.py
host_inspector/utils/stringutils.py
host_inspector-0.2.4.dist-info/licenses/AUTHORS.md
host_inspector-0.2.4.dist-info/licenses/LICENSE
host_inspector-0.2.4.dist-info/METADATA
host_inspector-0.2.4.dist-info/WHEEL
host_inspector-0.2.4.dist-info/top_level.txt
host_inspector-0.2.4.dist-info/RECORD
