Metadata-Version: 2.4
Name: host-inspector
Version: 0.2.4
Summary: A simple python package to gather host information from Windows, Mac and Linux. Returns host data as dicts to be used internally or sent to front-end dashboard applications as JSON.
Author-email: Tim Santor <tsantor@xstudios.com>
Project-URL: Repository, https://github.com/tsantor/host-inspector.git
Project-URL: Issues, https://github.com/tsantor/host-inspector/issues
Project-URL: Changelog, https://github.com/tsantor/host-inspector/blob/master/HISTORY.md
Classifier: Development Status :: 5 - Production/Stable
Classifier: Environment :: Console
Classifier: Intended Audience :: Developers
Classifier: Natural Language :: English
Classifier: Programming Language :: Python :: 3.10
Classifier: Programming Language :: Python :: 3.11
Classifier: Programming Language :: Python :: 3.12
Classifier: Programming Language :: Python :: 3.13
Requires-Python: >=3.10
License-File: LICENSE
License-File: AUTHORS.md
Requires-Dist: humanize>=4.14.0
Requires-Dist: psutil>=7.1.3
Requires-Dist: py-machineid>=0.8.1
Dynamic: license-file
